{
  "development": {
    "username": "ejjem",
    "password": "tigonlee10*",
    "database": "forum",
    "host": "127.0.0.1",
    "dialect": "mysql"
  },
  "test": {
    "username": "quipu0316",
    "password": "q0u3i1p6u",
    "database": "test",
    "host": "quipu.cd22uyeacdjw.ap-northeast-2.rds.amazonaws.com",
    "dialect": "mysql"
  },
  "production": {
    "username": "root",
    "password": null,
    "database": "database_production",
    "host": "127.0.0.1",
    "dialect": "mysql"
  }
}